CHANGES.txt
README.txt
setup.py
Products/__init__.py
Products.Zope_Hotfix_CVE_2011_3587.egg-info/PKG-INFO
Products.Zope_Hotfix_CVE_2011_3587.egg-info/SOURCES.txt
Products.Zope_Hotfix_CVE_2011_3587.egg-info/dependency_links.txt
Products.Zope_Hotfix_CVE_2011_3587.egg-info/namespace_packages.txt
Products.Zope_Hotfix_CVE_2011_3587.egg-info/not-zip-safe
Products.Zope_Hotfix_CVE_2011_3587.egg-info/requires.txt
Products.Zope_Hotfix_CVE_2011_3587.egg-info/top_level.txt
Products/Zope_Hotfix_CVE_2011_3587/__init__.py
Products/Zope_Hotfix_CVE_2011_3587/patch.py